{
	"files": [
		{
			"path": "style/styles.css",
			"bookmarks": [
				{
					"line": 7,
					"column": 7,
					"label": ""
				},
				{
					"line": 23,
					"column": 17,
					"label": ""
				},
				{
					"line": 28,
					"column": 2,
					"label": ""
				},
				{
					"line": 101,
					"column": 17,
					"label": ""
				},
				{
					"line": 133,
					"column": 3,
					"label": ""
				},
				{
					"line": 143,
					"column": 6,
					"label": ""
				},
				{
					"line": 174,
					"column": 21,
					"label": ""
				},
				{
					"line": 201,
					"column": 7,
					"label": ""
				},
				{
					"line": 244,
					"column": 10,
					"label": ""
				},
				{
					"line": 274,
					"column": 22,
					"label": ""
				},
				{
					"line": 351,
					"column": 15,
					"label": ""
				},
				{
					"line": 463,
					"column": 12,
					"label": ""
				},
				{
					"line": 472,
					"column": 29,
					"label": ""
				}
			]
		},
		{
			"path": "index.html",
			"bookmarks": [
				{
					"line": 44,
					"column": 13,
					"label": ""
				},
				{
					"line": 60,
					"column": 24,
					"label": ""
				},
				{
					"line": 88,
					"column": 23,
					"label": ""
				},
				{
					"line": 122,
					"column": 14,
					"label": ""
				}
			]
		},
		{
			"path": "about-bonzai.html",
			"bookmarks": [
				{
					"line": 74,
					"column": 16,
					"label": ""
				}
			]
		}
	]
}